{
  "undead_revamp2:theundeadchallenges": {
    "criteria": {
      "theundeadchallenges_0": "2025-03-16 22:46:29 +0000"
    },
    "done": true
  },
  "farmersdelight:main/root": {
    "criteria": {
      "seeds": "2025-03-16 22:46:29 +0000"
    },
    "done": true
  },
  "create:root": {
    "criteria": {
      "0": "2025-03-16 22:46:29 +0000"
    },
    "done": true
  },
  "naturescompass:natures_compass_log": {
    "criteria": {
      "has_recipe": "2025-03-16 22:46:29 +0000"
    },
    "done": true
  },
  "faded_conquest_2:faded_2": {
    "criteria": {
      "faded_2_0": "2025-03-16 22:46:29 +0000"
    },
    "done": true
  },
  "naturescompass:natures_compass": {
    "criteria": {
      "has_recipe": "2025-03-16 22:46:29 +0000"
    },
    "done": true
  },
  "naturescompass:natures_compass_sapling": {
    "criteria": {
      "has_recipe": "2025-03-16 22:46:29 +0000"
    },
    "done": true
  },
  "mowziesmobs:root": {
    "criteria": {
      "custom_test_name": "2025-03-16 22:46:29 +0000"
    },
    "done": true
  },
  "lootr:root": {
    "criteria": {
      "always_true": "2025-03-16 22:46:29 +0000"
    },
    "done": true
  },
  "born_in_chaos_v1:bornin_chaos": {
    "criteria": {
      "bornin_chaos_0": "2025-03-16 22:46:29 +0000"
    },
    "done": true
  },
  "betterdeserttemples:root": {
    "criteria": {
      "always": "2025-03-16 22:46:29 +0000"
    },
    "done": true
  },
  "cataclysm:root": {
    "criteria": {
      "custom_test_name": "2025-03-16 22:46:29 +0000"
    },
    "done": true
  },
  "biomesoplenty:biomesoplenty/root": {
    "criteria": {
      "rocky_shrubland": "2025-03-16 22:46:30 +0000"
    },
    "done": true
  },
  "biomesoplenty:biomesoplenty/all_biomes": {
    "criteria": {
      "woodland": "2025-03-16 23:15:15 +0000",
      "shrubland": "2025-03-16 22:49:29 +0000",
      "snowblossom_grove": "2025-03-30 17:30:01 +0000",
      "rocky_shrubland": "2025-03-16 22:46:30 +0000",
      "scrubland": "2025-03-16 23:13:10 +0000",
      "erupting_inferno": "2025-03-29 23:53:57 +0000",
      "highland": "2025-03-30 02:32:44 +0000",
      "cold_desert": "2025-03-29 01:05:42 +0000",
      "old_growth_woodland": "2025-03-28 23:38:15 +0000",
      "crystalline_chasm": "2025-03-29 23:53:10 +0000",
      "orchard": "2025-03-23 20:24:29 +0000",
      "field": "2025-03-30 02:39:38 +0000",
      "lavender_forest": "2025-03-30 19:04:48 +0000",
      "moor": "2025-03-22 03:29:36 +0000",
      "mediterranean_forest": "2025-03-28 23:37:27 +0000",
      "coniferous_forest": "2025-03-30 02:44:50 +0000",
      "spider_nest": "2025-03-23 20:58:31 +0000",
      "redwood_forest": "2025-03-22 03:26:24 +0000",
      "dune_beach": "2025-03-22 03:26:13 +0000",
      "volcano": "2025-03-22 03:20:00 +0000",
      "pasture": "2025-03-23 20:04:44 +0000",
      "rocky_rainforest": "2025-03-28 23:42:01 +0000",
      "volcanic_plains": "2025-03-22 03:19:33 +0000",
      "lavender_field": "2025-03-30 18:59:56 +0000",
      "fir_clearing": "2025-03-30 02:43:50 +0000",
      "grassland": "2025-03-22 03:29:45 +0000",
      "prairie": "2025-03-23 20:15:56 +0000",
      "snowy_coniferous_forest": "2025-03-29 01:06:12 +0000",
      "snowy_fir_clearing": "2025-03-29 01:25:54 +0000",
      "undergrowth": "2025-03-29 23:41:15 +0000",
      "origin_valley": "2025-03-30 17:11:55 +0000",
      "tropics": "2025-03-30 17:10:46 +0000",
      "rainforest": "2025-03-17 01:16:47 +0000",
      "ominous_woods": "2025-03-30 02:43:23 +0000"
    },
    "done": false
  },
  "tombstone:adventure/root": {
    "criteria": {
      "auto": "2025-03-16 22:46:30 +0000"
    },
    "done": true
  },
  "lootr:1chest": {
    "criteria": {
      "opened_chest": "2025-03-16 22:47:50 +0000"
    },
    "done": true
  },
  "lootr:social": {
    "criteria": {
      "opened_barrel": "2025-03-20 22:30:37 +0000",
      "opened_chest": "2025-03-16 22:47:50 +0000",
      "opened_cart": "2025-03-29 22:39:50 +0000"
    },
    "done": false
  },
  "farmersdelight:main/get_fd_seed": {
    "criteria": {
      "onion": "2025-03-16 22:47:56 +0000"
    },
    "done": true
  },
  "artifacts:amateur_archaeologist": {
    "criteria": {
      "find_artifact": "2025-03-16 22:48:01 +0000"
    },
    "done": true
  },
  "minecraft:adventure/sleep_in_bed": {
    "criteria": {
      "slept_in_bed": "2025-03-16 22:48:30 +0000"
    },
    "done": true
  },
  "lootr:10loot": {
    "criteria": {
      "loot_stat": "2025-03-16 22:51:29 +0000"
    },
    "done": true
  },
  "paraglider:root": {
    "criteria": {
      "crafting_table": "2025-03-16 22:53:18 +0000"
    },
    "done": true
  },
  "aquamirae:adventure/root": {
    "criteria": {
      "crafting_table": "2025-03-16 22:53:18 +0000"
    },
    "done": true
  },
  "minecraft:story/root": {
    "criteria": {
      "crafting_table": "2025-03-16 22:53:18 +0000"
    },
    "done": true
  },
  "farmersdelight:main/craft_knife": {
    "criteria": {
      "flint_knife": "2025-03-16 22:54:05 +0000"
    },
    "done": true
  },
  "minecraft:husbandry/balanced_diet": {
    "criteria": {
      "baked_potato": "2025-03-17 00:37:46 +0000",
      "beef": "2025-03-16 23:11:35 +0000",
      "porkchop": "2025-03-16 23:09:49 +0000",
      "apple": "2025-03-16 22:54:53 +0000",
      "pumpkin_pie": "2025-03-21 23:18:39 +0000",
      "mutton": "2025-03-17 00:00:25 +0000",
      "bread": "2025-03-17 00:13:15 +0000",
      "golden_apple": "2025-03-17 00:18:11 +0000",
      "suspicious_stew": "2025-03-21 01:02:13 +0000",
      "cookie": "2025-03-22 18:53:03 +0000",
      "golden_carrot": "2025-03-22 00:24:32 +0000",
      "cooked_salmon": "2025-03-22 02:37:03 +0000",
      "carrot": "2025-03-29 00:16:25 +0000"
    },
    "done": false
  },
  "minecraft:husbandry/root": {
    "criteria": {
      "consumed_item": "2025-03-16 22:54:53 +0000"
    },
    "done": true
  },
  "minecraft:story/mine_stone": {
    "criteria": {
      "get_stone": "2025-03-16 22:55:31 +0000"
    },
    "done": true
  },
  "minecraft:story/smelt_iron": {
    "criteria": {
      "iron": "2025-03-16 22:56:04 +0000"
    },
    "done": true
  },
  "minecraft:story/upgrade_tools": {
    "criteria": {
      "stone_pickaxe": "2025-03-16 22:56:43 +0000"
    },
    "done": true
  },
  "minecraft:adventure/adventuring_time": {
    "criteria": {
      "minecraft:taiga": "2025-03-30 02:38:13 +0000",
      "minecraft:deep_ocean": "2025-03-22 03:24:22 +0000",
      "minecraft:frozen_river": "2025-03-29 01:05:29 +0000",
      "quark:glimmering_weald": "2025-03-29 22:23:08 +0000",
      "minecraft:sunflower_plains": "2025-03-23 20:11:43 +0000",
      "minecraft:cherry_grove": "2025-03-30 02:37:01 +0000",
      "minecraft:birch_forest": "2025-03-22 17:14:41 +0000",
      "minecraft:bamboo_jungle": "2025-03-22 03:20:13 +0000",
      "minecraft:beach": "2025-03-22 03:26:12 +0000",
      "minecraft:stony_peaks": "2025-03-16 23:27:57 +0000",
      "minecraft:dark_forest": "2025-03-22 17:15:07 +0000",
      "minecraft:sparse_jungle": "2025-03-28 23:44:23 +0000",
      "minecraft:lukewarm_ocean": "2025-03-17 00:02:43 +0000",
      "minecraft:river": "2025-03-16 23:00:34 +0000",
      "minecraft:stony_shore": "2025-03-16 23:09:01 +0000",
      "minecraft:snowy_plains": "2025-03-23 04:08:13 +0000",
      "minecraft:dripstone_caves": "2025-03-22 21:03:50 +0000",
      "minecraft:snowy_taiga": "2025-03-29 01:30:43 +0000",
      "minecraft:jagged_peaks": "2025-03-21 22:52:42 +0000",
      "minecraft:cold_ocean": "2025-03-30 17:37:43 +0000",
      "minecraft:forest": "2025-03-21 22:25:05 +0000",
      "minecraft:deep_cold_ocean": "2025-03-29 00:38:02 +0000",
      "minecraft:frozen_ocean": "2025-03-29 01:05:00 +0000",
      "minecraft:deep_frozen_ocean": "2025-03-29 00:41:09 +0000",
      "minecraft:jungle": "2025-03-17 01:19:46 +0000",
      "minecraft:ocean": "2025-03-22 03:24:42 +0000",
      "minecraft:snowy_beach": "2025-03-30 17:37:19 +0000",
      "minecraft:deep_lukewarm_ocean": "2025-03-22 03:24:00 +0000",
      "minecraft:flower_forest": "2025-03-23 04:15:38 +0000",
      "minecraft:old_growth_birch_forest": "2025-03-30 02:37:54 +0000",
      "minecraft:deep_dark": "2025-03-23 04:16:00 +0000",
      "minecraft:meadow": "2025-03-16 23:27:02 +0000",
      "minecraft:savanna": "2025-03-22 18:41:37 +0000",
      "minecraft:plains": "2025-03-23 19:54:10 +0000"
    },
    "done": false
  },
  "minecraft:story/obtain_armor": {
    "criteria": {
      "iron_helmet": "2025-03-16 23:04:54 +0000"
    },
    "done": true
  },
  "minecraft:story/iron_tools": {
    "criteria": {
      "iron_pickaxe": "2025-03-16 23:04:57 +0000"
    },
    "done": true
  },
  "minecraft:adventure/root": {
    "criteria": {
      "killed_something": "2025-03-16 23:13:18 +0000"
    },
    "done": true
  },
  "lootr:25loot": {
    "criteria": {
      "loot_stat": "2025-03-16 23:15:49 +0000"
    },
    "done": true
  },
  "lootr:50loot": {
    "criteria": {
      "loot_stat": "2025-03-16 23:41:55 +0000"
    },
    "done": true
  },
  "alexscaves:alexscaves/cave_tablet": {
    "criteria": {
      "cave_tablet": "2025-03-16 23:44:20 +0000"
    },
    "done": true
  },
  "minecraft:adventure/kill_all_mobs": {
    "criteria": {
      "minecraft:blaze": "2025-03-22 00:24:58 +0000",
      "minecraft:pillager": "2025-03-23 19:03:51 +0000",
      "minecraft:skeleton": "2025-03-20 22:04:30 +0000",
      "minecraft:ravager": "2025-03-23 19:03:50 +0000",
      "minecraft:hoglin": "2025-03-22 00:52:15 +0000",
      "minecraft:vindicator": "2025-03-23 18:56:57 +0000",
      "minecraft:magma_cube": "2025-03-22 00:41:43 +0000",
      "minecraft:spider": "2025-03-20 22:11:51 +0000",
      "minecraft:piglin_brute": "2025-03-30 00:01:13 +0000",
      "minecraft:creeper": "2025-03-20 22:48:47 +0000",
      "minecraft:slime": "2025-03-22 00:59:27 +0000",
      "minecraft:phantom": "2025-03-22 01:51:23 +0000",
      "minecraft:witch": "2025-03-20 22:16:48 +0000",
      "minecraft:wither_skeleton": "2025-03-22 00:24:10 +0000",
      "minecraft:cave_spider": "2025-03-29 22:37:16 +0000",
      "minecraft:enderman": "2025-03-22 20:33:27 +0000",
      "minecraft:vex": "2025-03-16 23:44:56 +0000",
      "minecraft:zombie": "2025-03-20 22:01:36 +0000",
      "quark:foxhound": "2025-03-30 00:08:46 +0000",
      "minecraft:zombie_villager": "2025-03-21 23:39:22 +0000"
    },
    "done": false
  },
  "minecraft:adventure/kill_a_mob": {
    "criteria": {
      "minecraft:vex": "2025-03-16 23:44:56 +0000"
    },
    "done": true
  },
  "knightquest:knightquest": {
    "criteria": {
      "requirement": "2025-03-16 23:47:33 +0000"
    },
    "done": true
  },
  "tombstone:adventure/create_familiar_receptacle": {
    "criteria": {
      "has_receptacle_of_familiar": "2025-03-17 00:02:21 +0000"
    },
    "done": true
  },
  "tombstone:adventure/first_knowledge": {
    "criteria": {
      "coded_trigger": "2025-03-17 00:02:21 +0000"
    },
    "done": true
  },
  "tombstone:adventure/create_magic_scroll": {
    "criteria": {
      "has_magic_scroll": "2025-03-17 00:05:10 +0000"
    },
    "done": true
  },
  "minecraft:adventure/trade": {
    "criteria": {
      "traded": "2025-03-17 00:26:28 +0000"
    },
    "done": true
  },
  "portablemobs:basiccelladvancement": {
    "criteria": {
      "basiccell": "2025-03-17 00:57:39 +0000"
    },
    "done": true
  },
  "create:copper": {
    "criteria": {
      "0": "2025-03-17 00:57:57 +0000"
    },
    "done": true
  },
  "minecraft:adventure/shoot_arrow": {
    "criteria": {
      "shot_arrow": "2025-03-17 01:14:24 +0000"
    },
    "done": true
  },
  "alexsmobs:alexsmobs/seagull_steal": {
    "criteria": {
      "ex": "2025-03-17 01:18:57 +0000"
    },
    "done": true
  },
  "minecraft:story/deflect_arrow": {
    "criteria": {
      "deflected_projectile": "2025-03-20 22:04:21 +0000"
    },
    "done": true
  },
  "tombstone:adventure/first_grave": {
    "criteria": {
      "coded_trigger": "2025-03-20 22:13:05 +0000"
    },
    "done": true
  },
  "tombstone:adventure/strong_or_careful": {
    "criteria": {
      "coded_trigger": "2025-03-20 22:13:05 +0000"
    },
    "done": true
  },
  "tombstone:recipes/from_grave_key": {
    "criteria": {
      "has_ingredient": "2025-03-20 22:13:11 +0000"
    },
    "done": true
  },
  "tombstone:adventure/ashes_and_bones": {
    "criteria": {
      "coded_trigger": "2025-03-20 22:16:27 +0000"
    },
    "done": true
  },
  "tombstone:adventure/ambush": {
    "criteria": {
      "coded_trigger": "2025-03-20 22:16:48 +0000"
    },
    "done": true
  },
  "tombstone:adventure/find_grave_dust": {
    "criteria": {
      "from_undead": "2025-03-20 22:17:15 +0000"
    },
    "done": true
  },
  "tombstone:recipes/from_grave_dust": {
    "criteria": {
      "has_ingredient": "2025-03-20 22:17:39 +0000"
    },
    "done": true
  },
  "minecraft:story/mine_diamond": {
    "criteria": {
      "diamond": "2025-03-20 22:27:51 +0000"
    },
    "done": true
  },
  "lootr:1barrel": {
    "criteria": {
      "opened_barrel": "2025-03-20 22:30:37 +0000"
    },
    "done": true
  },
  "undead_revamp2:nightnight": {
    "criteria": {
      "nightnight_0": "2025-03-20 22:32:03 +0000"
    },
    "done": true
  },
  "artifacts:chest_slayer": {
    "criteria": {
      "kill_mimic": "2025-03-20 22:48:09 +0000"
    },
    "done": true
  },
  "undead_revamp2:nowyouknow": {
    "criteria": {
      "nowyouknow_0": "2025-03-20 22:51:26 +0000"
    },
    "done": true
  },
  "farmersdelight:main/plant_all_crops": {
    "criteria": {
      "sugar_cane": "2025-03-22 00:12:52 +0000",
      "potato": "2025-03-20 23:39:24 +0000"
    },
    "done": false
  },
  "minecraft:story/shiny_gear": {
    "criteria": {
      "diamond_chestplate": "2025-03-20 23:41:11 +0000"
    },
    "done": true
  },
  "lootr:100loot": {
    "criteria": {
      "loot_stat": "2025-03-21 00:30:53 +0000"
    },
    "done": true
  },
  "undead_revamp2:defeatundeadbosses": {
    "criteria": {
      "defeatundeadbosses_0": "2025-03-21 00:48:50 +0000"
    },
    "done": true
  },
  "undead_revamp2:mommy": {
    "criteria": {
      "mommy_0": "2025-03-21 00:48:50 +0000"
    },
    "done": true
  },
  "supplementaries:husbandry/sus_stew": {
    "criteria": {
      "stew": "2025-03-21 01:02:13 +0000"
    },
    "done": true
  },
  "tombstone:adventure/easter": {
    "criteria": {
      "coded_trigger": "2025-03-21 21:49:02 +0000"
    },
    "done": true
  },
  "graveyard:graveyard/kill_graveyard_mob": {
    "criteria": {
      "skeleton_creeper": "2025-03-21 22:17:18 +0000"
    },
    "done": true
  },
  "tombstone:adventure/cancel_ghostly_shape": {
    "criteria": {
      "coded_trigger": "2025-03-21 22:41:47 +0000"
    },
    "done": true
  },
  "alexscaves:alexscaves/discover_toxic_caves": {
    "criteria": {
      "discover": "2025-03-21 22:42:42 +0000"
    },
    "done": true
  },
  "tombstone:adventure/enchant_grave_key": {
    "criteria": {
      "has_upgraded_grave_key": "2025-03-21 22:49:37 +0000"
    },
    "done": true
  },
  "tombstone:adventure/teleport_to_grave": {
    "criteria": {
      "coded_trigger": "2025-03-21 22:49:46 +0000"
    },
    "done": true
  },
  "alexscaves:alexscaves/root": {
    "criteria": {
      "underground_cabin": "2025-03-21 23:08:03 +0000"
    },
    "done": true
  },
  "alexscaves:alexscaves/cave_codex": {
    "criteria": {
      "cave_codex": "2025-03-21 23:29:34 +0000"
    },
    "done": true
  },
  "tombstone:adventure/bone_crusher": {
    "criteria": {
      "coded_trigger": "2025-03-21 23:39:22 +0000"
    },
    "done": true
  },
  "born_in_chaos_v1:charm_collector": {
    "criteria": {
      "charm_collector_1": "2025-03-23 19:12:17 +0000",
      "charm_collector_0": "2025-03-23 19:17:00 +0000",
      "charm_collector_4": "2025-03-21 23:39:57 +0000",
      "charm_collector_2": "2025-03-23 19:12:17 +0000"
    },
    "done": false
  },
  "born_in_chaos_v1:dark_metallurgy": {
    "criteria": {
      "dark_metallurgy_0": "2025-03-21 23:39:57 +0000"
    },
    "done": true
  },
  "tombstone:adventure/use_feather_fall": {
    "criteria": {
      "has_magic_scroll": "2025-03-21 23:47:20 +0000"
    },
    "done": true
  },
  "minecraft:adventure/totem_of_undying": {
    "criteria": {
      "used_totem": "2025-03-21 23:48:28 +0000"
    },
    "done": true
  },
  "mowziesmobs:kill_ferrous_wroughtnaut": {
    "criteria": {
      "ferrous_wroughtnaut": "2025-03-21 23:51:19 +0000"
    },
    "done": true
  },
  "alexscaves:alexscaves/cave_map": {
    "criteria": {
      "cave_map": "2025-03-22 00:14:43 +0000"
    },
    "done": true
  },
  "tombstone:adventure/stolen_magic": {
    "criteria": {
      "coded_trigger": "2025-03-22 00:20:24 +0000"
    },
    "done": true
  },
  "tombstone:adventure/magic_siphoner": {
    "criteria": {
      "coded_trigger": "2025-03-22 00:20:40 +0000"
    },
    "done": true
  },
  "tombstone:adventure/find_easter_egg": {
    "criteria": {
      "coded_trigger": "2025-03-22 00:21:29 +0000"
    },
    "done": true
  },
  "minecraft:nether/root": {
    "criteria": {
      "entered_nether": "2025-03-22 00:22:14 +0000"
    },
    "done": true
  },
  "minecraft:story/enter_the_nether": {
    "criteria": {
      "entered_nether": "2025-03-22 00:22:14 +0000"
    },
    "done": true
  },
  "minecraft:nether/explore_nether": {
    "criteria": {
      "minecraft:crimson_forest": "2025-03-22 00:22:15 +0000",
      "minecraft:nether_wastes": "2025-03-22 00:45:40 +0000",
      "minecraft:soul_sand_valley": "2025-03-29 23:56:29 +0000",
      "minecraft:basalt_deltas": "2025-03-29 23:55:08 +0000",
      "minecraft:warped_forest": "2025-03-29 23:59:53 +0000"
    },
    "done": true
  },
  "minecraft:nether/find_fortress": {
    "criteria": {
      "in_better_fortress": "2025-03-22 00:22:36 +0000"
    },
    "done": true
  },
  "minecraft:nether/obtain_blaze_rod": {
    "criteria": {
      "blaze_rod": "2025-03-22 00:25:28 +0000"
    },
    "done": true
  },
  "minecraft:nether/get_wither_skull": {
    "criteria": {
      "wither_skull": "2025-03-22 00:28:39 +0000"
    },
    "done": true
  },
  "minecraft:story/form_obsidian": {
    "criteria": {
      "obsidian": "2025-03-22 00:39:58 +0000"
    },
    "done": true
  },
  "minecraft:nether/find_bastion": {
    "criteria": {
      "bastion": "2025-03-22 00:45:40 +0000"
    },
    "done": true
  },
  "paraglider:pray_to_the_goddess": {
    "criteria": {
      "bargain": "2025-03-22 01:16:14 +0000"
    },
    "done": true
  },
  "minecraft:adventure/lightning_rod_with_villager_no_fire": {
    "criteria": {
      "lightning_rod_with_villager_no_fire": "2025-03-22 01:50:14 +0000"
    },
    "done": true
  },
  "deeperdarker:main/kill_all_sculk_mobs": {
    "criteria": {
      "shattered": "2025-03-29 22:46:52 +0000",
      "phantom": "2025-03-22 01:51:23 +0000",
      "sculk_centipede": "2025-03-29 22:47:53 +0000",
      "sculk_leech": "2025-03-29 22:42:54 +0000"
    },
    "done": false
  },
  "tombstone:adventure/discreet_search": {
    "criteria": {
      "coded_trigger": "2025-03-22 01:53:14 +0000"
    },
    "done": true
  },
  "tombstone:adventure/funeral_theft": {
    "criteria": {
      "coded_trigger": "2025-03-22 01:53:14 +0000"
    },
    "done": true
  },
  "born_in_chaos_v1:good_demoman": {
    "criteria": {
      "good_demoman_0": "2025-03-22 02:34:21 +0000"
    },
    "done": true
  },
  "graveyard:graveyard/root": {
    "criteria": {
      "grave_01": "2025-03-22 03:26:47 +0000"
    },
    "done": true
  },
  "alexscaves:alexscaves/discover_primordial_caves": {
    "criteria": {
      "discover": "2025-03-22 17:18:26 +0000"
    },
    "done": true
  },
  "portablemobs:captureadvancement": {
    "criteria": {
      "capture": "2025-03-22 18:03:10 +0000"
    },
    "done": true
  },
  "minecraft:husbandry/bred_all_animals": {
    "criteria": {
      "minecraft:bee": "2025-03-22 18:56:02 +0000"
    },
    "done": false
  },
  "minecraft:husbandry/breed_an_animal": {
    "criteria": {
      "bred": "2025-03-22 18:56:02 +0000"
    },
    "done": true
  },
  "born_in_chaos_v1:exorcism": {
    "criteria": {
      "exorcism_0": "2025-03-22 19:07:46 +0000"
    },
    "done": true
  },
  "tombstone:adventure/neighborhood_brawl": {
    "criteria": {
      "coded_trigger": "2025-03-22 19:08:58 +0000"
    },
    "done": true
  },
  "tombstone:adventure/fortuitous_militia": {
    "criteria": {
      "coded_trigger": "2025-03-22 19:48:13 +0000"
    },
    "done": true
  },
  "born_in_chaos_v1:fighting_nightmares": {
    "criteria": {
      "fighting_nightmares_0": "2025-03-22 19:50:20 +0000"
    },
    "done": true
  },
  "minecraft:story/cure_zombie_villager": {
    "criteria": {
      "cured_zombie": "2025-03-22 19:55:41 +0000"
    },
    "done": true
  },
  "born_in_chaos_v1:the_wind_darkening": {
    "criteria": {
      "the_wind_darkening_0": "2025-03-22 20:25:27 +0000"
    },
    "done": true
  },
  "alexscaves:alexscaves/limestone": {
    "criteria": {
      "limestone": "2025-03-22 20:48:12 +0000"
    },
    "done": true
  },
  "minecraft:husbandry/tame_an_animal": {
    "criteria": {
      "tamed_animal": "2025-03-22 20:51:02 +0000"
    },
    "done": true
  },
  "alexscaves:alexscaves/tame_vallumraptor": {
    "criteria": {
      "killed": "2025-03-22 20:51:02 +0000"
    },
    "done": true
  },
  "alexscaves:alexscaves/discover_dinosaur": {
    "criteria": {
      "killed_by_tremorsaurus": "2025-03-22 20:51:30 +0000"
    },
    "done": true
  },
  "alexscaves:alexscaves/tree_star": {
    "criteria": {
      "tree_star": "2025-03-22 20:52:25 +0000"
    },
    "done": true
  },
  "alexscaves:alexscaves/defeat_big_dinosaur": {
    "criteria": {
      "killed_grottoceratops": "2025-03-22 20:52:47 +0000"
    },
    "done": true
  },
  "minecraft:end/root": {
    "criteria": {
      "entered_end": "2025-03-22 20:57:38 +0000"
    },
    "done": true
  },
  "minecraft:story/enter_the_end": {
    "criteria": {
      "entered_end": "2025-03-22 20:57:38 +0000"
    },
    "done": true
  },
  "graveyard:graveyard/crypt": {
    "criteria": {
      "crypt": "2025-03-22 21:02:15 +0000"
    },
    "done": true
  },
  "graveyard:graveyard/corruption": {
    "criteria": {
      "corruption": "2025-03-22 21:06:18 +0000"
    },
    "done": true
  },
  "graveyard:graveyard/dark_iron": {
    "criteria": {
      "dark_iron": "2025-03-22 21:07:57 +0000"
    },
    "done": true
  },
  "graveyard:graveyard/kill_wraith": {
    "criteria": {
      "wraith": "2025-03-22 21:07:58 +0000"
    },
    "done": true
  },
  "minecraft:nether/brew_potion": {
    "criteria": {
      "potion": "2025-03-22 22:05:35 +0000"
    },
    "done": true
  },
  "portablemobs:mastercelladvancement": {
    "criteria": {
      "mastercell": "2025-03-22 22:12:46 +0000"
    },
    "done": true
  },
  "minecraft:nether/obtain_ancient_debris": {
    "criteria": {
      "ancient_debris": "2025-03-23 00:26:47 +0000"
    },
    "done": true
  },
  "undead_revamp2:mygothgf": {
    "criteria": {
      "mygothgf_0": "2025-03-23 03:09:13 +0000"
    },
    "done": true
  },
  "alexscaves:alexscaves/summon_luxtructosaurus": {
    "criteria": {
      "summon_luxtructosaurus": "2025-03-23 03:19:41 +0000"
    },
    "done": true
  },
  "alexscaves:alexscaves/extinction_spear": {
    "criteria": {
      "dreadbow": "2025-03-23 03:38:42 +0000"
    },
    "done": true
  },
  "alexscaves:alexscaves/cave_book": {
    "criteria": {
      "cave_book": "2025-03-23 04:10:10 +0000"
    },
    "done": true
  },
  "minecraft:adventure/avoid_vibration": {
    "criteria": {
      "avoid_vibration": "2025-03-23 04:15:58 +0000"
    },
    "done": true
  },
  "deeperdarker:main/root": {
    "criteria": {
      "deep_dark": "2025-03-23 04:16:00 +0000"
    },
    "done": true
  },
  "illageandspillage:kill_all_iands": {
    "criteria": {
      "illageandspillage:preserver": "2025-03-23 19:06:24 +0000",
      "illageandspillage:engineer": "2025-03-23 19:11:30 +0000",
      "illageandspillage:igniter": "2025-03-23 18:53:36 +0000"
    },
    "done": false
  },
  "minecraft:adventure/voluntary_exile": {
    "criteria": {
      "voluntary_exile": "2025-03-23 18:56:57 +0000"
    },
    "done": true
  },
  "born_in_chaos_v1:dark_creator": {
    "criteria": {
      "dark_creator_0": "2025-03-23 19:16:59 +0000"
    },
    "done": true
  },
  "minecraft:adventure/hero_of_the_village": {
    "criteria": {
      "hero_of_the_village": "2025-03-23 19:17:01 +0000"
    },
    "done": true
  },
  "minecraft:adventure/kill_mob_near_sculk_catalyst": {
    "criteria": {
      "kill_mob_near_sculk_catalyst": "2025-03-23 20:01:09 +0000"
    },
    "done": true
  },
  "undead_revamp2:sugarcoat": {
    "criteria": {
      "sugarcoat_0": "2025-03-23 20:16:40 +0000"
    },
    "done": true
  },
  "minecraft:adventure/ol_betsy": {
    "criteria": {
      "shot_crossbow": "2025-03-28 23:46:52 +0000"
    },
    "done": true
  },
  "born_in_chaos_v1:big_boy": {
    "criteria": {
      "big_boy_0": "2025-03-28 23:54:44 +0000"
    },
    "done": true
  },
  "tombstone:adventure/create_magic_tablet": {
    "criteria": {
      "has_magic_tablet": "2025-03-29 00:04:26 +0000"
    },
    "done": true
  },
  "mowziesmobs:kill_umvuthi": {
    "criteria": {
      "barako": "2025-03-29 00:12:08 +0000"
    },
    "done": true
  },
  "alexscaves:alexscaves/discover_abyssal_chasm": {
    "criteria": {
      "discover": "2025-03-29 00:40:42 +0000"
    },
    "done": true
  },
  "aquamirae:adventure/find_ice_maze": {
    "criteria": {
      "deep_frozen_ocean": "2025-03-29 00:41:09 +0000"
    },
    "done": true
  },
  "alexscaves:alexscaves/hatch_tremorzilla_egg": {
    "criteria": {
      "hatch_tremorzilla_egg": "2025-03-29 00:49:56 +0000"
    },
    "done": true
  },
  "minecraft:adventure/walk_on_powder_snow_with_leather_boots": {
    "criteria": {
      "walk_on_powder_snow_with_leather_boots": "2025-03-29 01:14:19 +0000"
    },
    "done": true
  },
  "mowziesmobs:kill_frostmaw": {
    "criteria": {
      "frostmaw": "2025-03-29 01:16:11 +0000"
    },
    "done": true
  },
  "twilightforest:root": {
    "criteria": {
      "in_tf": "2025-03-29 01:17:26 +0000"
    },
    "done": true
  },
  "alexscaves:alexscaves/deep_one_items": {
    "criteria": {
      "magic_conch": "2025-03-29 20:52:06 +0000"
    },
    "done": false
  },
  "alexscaves:alexscaves/discover_magnetic_caves": {
    "criteria": {
      "discover": "2025-03-29 21:08:57 +0000"
    },
    "done": true
  },
  "alexscaves:alexscaves/defeat_notor": {
    "criteria": {
      "killed": "2025-03-29 21:11:08 +0000"
    },
    "done": true
  },
  "alexscaves:alexscaves/telecore": {
    "criteria": {
      "limestone": "2025-03-29 21:11:21 +0000"
    },
    "done": true
  },
  "alexscaves:alexscaves/neodymium": {
    "criteria": {
      "scarlet": "2025-03-29 21:19:53 +0000",
      "azure": "2025-03-29 21:11:23 +0000"
    },
    "done": true
  },
  "alexscaves:alexscaves/defeat_boundroid": {
    "criteria": {
      "killed": "2025-03-29 21:13:44 +0000"
    },
    "done": true
  },
  "alexscaves:alexscaves/defeat_magnetron": {
    "criteria": {
      "killed": "2025-03-29 21:18:31 +0000"
    },
    "done": true
  },
  "alexscaves:alexscaves/neodymium_ingot": {
    "criteria": {
      "azure": "2025-03-29 21:56:37 +0000"
    },
    "done": true
  },
  "alexscaves:alexscaves/resistor_shield": {
    "criteria": {
      "resistor_shield": "2025-03-29 21:58:34 +0000"
    },
    "done": true
  },
  "minecraft:adventure/trim_with_all_exclusive_armor_patterns": {
    "criteria": {
      "armor_trimmed_minecraft:vex_armor_trim_smithing_template_smithing_trim": "2025-03-29 22:19:09 +0000",
      "armor_trimmed_minecraft:ward_armor_trim_smithing_template_smithing_trim": "2025-03-30 01:01:49 +0000"
    },
    "done": false
  },
  "minecraft:adventure/trim_with_any_armor_pattern": {
    "criteria": {
      "armor_trimmed_minecraft:vex_armor_trim_smithing_template_smithing_trim": "2025-03-29 22:19:09 +0000"
    },
    "done": true
  },
  "deeperdarker:main/find_ancient_city": {
    "criteria": {
      "ancient_city": "2025-03-29 22:20:31 +0000"
    },
    "done": true
  },
  "born_in_chaos_v1:deceived_hopes": {
    "criteria": {
      "deceived_hopes_0": "2025-03-29 22:26:06 +0000"
    },
    "done": true
  },
  "tombstone:adventure/create_voodoo_poppet": {
    "criteria": {
      "has_voodoo_poppet": "2025-03-29 22:34:52 +0000"
    },
    "done": true
  },
  "tombstone:adventure/enchant_voodoo_poppet": {
    "criteria": {
      "has_enchanted_voodoo_poppet": "2025-03-29 22:34:52 +0000"
    },
    "done": true
  },
  "lootr:1cart": {
    "criteria": {
      "opened_cart": "2025-03-29 22:39:50 +0000"
    },
    "done": true
  },
  "deeperdarker:main/enter_otherside": {
    "criteria": {
      "otherside": "2025-03-29 22:41:33 +0000"
    },
    "done": true
  },
  "deeperdarker:main/explore_otherside": {
    "criteria": {
      "deeplands": "2025-03-29 22:41:34 +0000"
    },
    "done": false
  },
  "deeperdarker:main/find_ancient_temple": {
    "criteria": {
      "ancient_temple": "2025-03-29 22:51:40 +0000"
    },
    "done": true
  },
  "minecraft:nether/loot_bastion": {
    "criteria": {
      "loot_bastion_hoglin_stable": "2025-03-30 00:02:48 +0000"
    },
    "done": true
  },
  "cataclysm:find_burning_arena": {
    "criteria": {
      "arena": "2025-03-30 00:34:42 +0000"
    },
    "done": true
  },
  "cataclysm:find_frosted_prison": {
    "criteria": {
      "prison": "2025-03-30 02:44:50 +0000"
    },
    "done": true
  },
  "cataclysm:find_sunken_city": {
    "criteria": {
      "factory": "2025-03-30 17:38:50 +0000"
    },
    "done": true
  },
  "tombstone:adventure/chain_death": {
    "criteria": {
      "coded_trigger": "2025-03-30 17:44:27 +0000"
    },
    "done": true
  },
  "DataVersion": 3465
}